nerblackbox/MLproject
nerblackbox/__about__.py
nerblackbox/__init__.py
nerblackbox/cli.py
nerblackbox/api/__init__.py
nerblackbox/api/annotation_tool.py
nerblackbox/api/dataset.py
nerblackbox/api/model.py
nerblackbox/api/store.py
nerblackbox/api/training.py
nerblackbox/api/utils.py
nerblackbox/modules/__init__.py
nerblackbox/modules/training_results.py
nerblackbox/modules/annotation/__init__.py
nerblackbox/modules/annotation/annotation_tool_base.py
nerblackbox/modules/annotation/annotation_tool_doccano.py
nerblackbox/modules/annotation/annotation_tool_labelstudio.py
nerblackbox/modules/annotation/colors.py
nerblackbox/modules/annotation/file_conversion.py
nerblackbox/modules/annotation/io.py
nerblackbox/modules/annotation/utils.py
nerblackbox/modules/data/datasets/.gitignore
nerblackbox/modules/data/pretrained_models/.gitignore
nerblackbox/modules/data/training_configs/.gitignore
nerblackbox/modules/data/training_configs/default.ini
nerblackbox/modules/data/training_configs/my_training_conll2003.ini
nerblackbox/modules/data/training_configs/my_training_example.ini
nerblackbox/modules/data/training_configs/my_training_sic.ini
nerblackbox/modules/data/training_configs/my_training_suc.ini
nerblackbox/modules/data/training_configs/my_training_swe_nerc.ini
nerblackbox/modules/data/training_configs/my_training_swedish_ner_corpus.ini
nerblackbox/modules/datasets/__init__.py
nerblackbox/modules/datasets/analyzer.py
nerblackbox/modules/datasets/plots.py
nerblackbox/modules/datasets/formatter/__init__.py
nerblackbox/modules/datasets/formatter/auto_formatter.py
nerblackbox/modules/datasets/formatter/base_formatter.py
nerblackbox/modules/datasets/formatter/conll2003_formatter.py
nerblackbox/modules/datasets/formatter/huggingface_datasets_formatter.py
nerblackbox/modules/datasets/formatter/sic_formatter.py
nerblackbox/modules/datasets/formatter/suc_formatter.py
nerblackbox/modules/datasets/formatter/sucx_formatter.py
nerblackbox/modules/datasets/formatter/swe_nerc_formatter.py
nerblackbox-1.0.0.dist-info/LICENSE.txt
nerblackbox-1.0.0.dist-info/METADATA
nerblackbox-1.0.0.dist-info/WHEEL
nerblackbox-1.0.0.dist-info/entry_points.txt
nerblackbox-1.0.0.dist-info/top_level.txt
nerblackbox-1.0.0.dist-info/RECORD
