Metadata-Version: 2.1
Name: nerblackbox
Version: 1.0.0
Summary: a high-level library for named entity recognition in python
Home-page: https://pypi.org/project/nerblackbox
Author: Felix Stollenwerk
Author-email: felix.stollenwerk@ai.se
License: Apache 2.0
Keywords: NLP,NER,named entity recognition,BERT,transformer,pytorch
Platform: UNKNOWN
Classifier: License :: OSI Approved :: Apache Software License
Classifier: Development Status :: 4 - Beta
Classifier: Programming Language :: Python :: 3.8
Classifier: Programming Language :: Python :: 3.9
Classifier: Programming Language :: Python :: 3.10
Classifier: Operating System :: Unix
Classifier: Topic :: Text Processing :: Linguistic
Classifier: Topic :: Scientific/Engineering :: Artificial Intelligence
Classifier: Intended Audience :: Developers
Classifier: Intended Audience :: Education
Classifier: Intended Audience :: Science/Research
Requires-Python: >=3.8
License-File: LICENSE.txt
Requires-Dist: matplotlib (~=3.5.2)
Requires-Dist: mlflow (~=2.6.0)
Requires-Dist: pytorch-lightning (~=1.9.3)
Requires-Dist: omegaconf (~=2.2.2)
Requires-Dist: seqeval (~=1.2.2)
Requires-Dist: scikit-learn (~=1.1.1)
Requires-Dist: tensorboard (~=2.13.0)
Requires-Dist: tensorboardX (~=2.5.1)
Requires-Dist: transformers (~=4.31.0)
Requires-Dist: numpy (~=1.23.4)
Requires-Dist: datasets (~=2.9.0)
Requires-Dist: evaluate (~=0.4.0)
Requires-Dist: torchmetrics (~=0.11.1)
Requires-Dist: notebook (~=6.5.3)
Requires-Dist: ipywidgets (~=8.0.4)
Requires-Dist: doccano-client (~=1.2.7)
Requires-Dist: label-studio-sdk (~=0.0.19)
Requires-Dist: sentencepiece (~=0.1.99)
Provides-Extra: dev
Requires-Dist: black ; extra == 'dev'
Requires-Dist: coverage ; extra == 'dev'
Requires-Dist: jupyter ; extra == 'dev'
Requires-Dist: mkdocs-click ; extra == 'dev'
Requires-Dist: mkdocs-material ; extra == 'dev'
Requires-Dist: mkdocstrings[python] ; extra == 'dev'
Requires-Dist: mypy (~=1.0.0) ; extra == 'dev'
Requires-Dist: pip-chill ; extra == 'dev'
Requires-Dist: pylint ; extra == 'dev'
Requires-Dist: pytest ; extra == 'dev'
Requires-Dist: twine ; extra == 'dev'
Requires-Dist: tox ; extra == 'dev'
Requires-Dist: types-requests (~=2.28.11.13) ; extra == 'dev'
Requires-Dist: types-setuptools (~=67.3.0.1) ; extra == 'dev'
